google_automation_mcp/__init__.py
google_automation_mcp/appscript_tools.py
google_automation_mcp/cli.py
google_automation_mcp/server.py
google_automation_mcp/server_appscript.py
google_automation_mcp/server_auth.py
google_automation_mcp/server_workspace.py
google_automation_mcp/setup.py
google_automation_mcp/auth/__init__.py
google_automation_mcp/auth/clasp.py
google_automation_mcp/auth/credential_store.py
google_automation_mcp/auth/google_auth.py
google_automation_mcp/auth/oauth_config.py
google_automation_mcp/auth/scopes.py
google_automation_mcp/auth/service_adapter.py
google_automation_mcp/core/__init__.py
google_automation_mcp/core/context.py
google_automation_mcp/tools/__init__.py
google_automation_mcp/tools/auth_tools.py
google_automation_mcp/tools/calendar.py
google_automation_mcp/tools/docs.py
google_automation_mcp/tools/drive.py
google_automation_mcp/tools/error_handler.py
google_automation_mcp/tools/gmail.py
google_automation_mcp/tools/sheets.py
google_automation_mcp-0.5.2.dist-info/METADATA
google_automation_mcp-0.5.2.dist-info/WHEEL
google_automation_mcp-0.5.2.dist-info/entry_points.txt
google_automation_mcp-0.5.2.dist-info/licenses/LICENSE
google_automation_mcp-0.5.2.dist-info/RECORD
