Metadata-Version: 2.4
Name: google-automation-mcp
Version: 0.5.2
Summary: Headless Google Workspace automation for AI - Apps Script, Gmail, Drive, Sheets, Calendar, Docs
License: MIT
License-File: LICENSE
Keywords: ai,apps-script,automation,calendar,drive,gmail,google,mcp,sheets,workspace
Classifier: Development Status :: 4 - Beta
Classifier: Intended Audience :: Developers
Classifier: License :: OSI Approved :: MIT License
Classifier: Programming Language :: Python :: 3
Classifier: Programming Language :: Python :: 3.10
Classifier: Programming Language :: Python :: 3.11
Classifier: Programming Language :: Python :: 3.12
Requires-Python: >=3.10
Requires-Dist: fastmcp>=2.0.0
Requires-Dist: google-api-python-client>=2.0.0
Requires-Dist: google-auth-oauthlib>=1.0.0
Requires-Dist: google-auth>=2.0.0
Requires-Dist: pyjwt>=2.0.0
Provides-Extra: dev
Requires-Dist: pytest-asyncio>=0.21.0; extra == 'dev'
Requires-Dist: pytest>=7.0.0; extra == 'dev'
